{
  "key": "hou_po",
  "name_zh": "厚朴",
  "ok": true,
  "resolve": "wikidata:Q1042288",
  "filename": "Magnolia officinalis habit.jpg",
  "commons_title": "File:Magnolia officinalis habit.jpg",
  "source_page": "https://commons.wikimedia.org/wiki/File%3AMagnolia%20officinalis%20habit.jpg",
  "license": "CC BY-SA 3.0",
  "license_url": "https://creativecommons.org/licenses/by-sa/3.0",
  "artist": "Bruce Marlin",
  "credit": "Own work http://www.cirrusimage.com/tree_magnolia_houpu.htm",
  "sketch": "/media/herbs/hou_po/sketch.png",
  "source": "/media/herbs/hou_po/source.jpg",
  "attribution": "Image: Bruce Marlin / CC BY-SA 3.0; pencil sketch derived locally for Herba Atlas."
}