{
  "key": "jiang_can",
  "name_zh": "僵蚕",
  "ok": true,
  "resolve": "wikidata-search:Q55694576",
  "filename": "Pairedmoths.jpg",
  "commons_title": "File:Pairedmoths.jpg",
  "source_page": "https://commons.wikimedia.org/wiki/File%3APairedmoths.jpg",
  "license": "CC BY-SA 2.5",
  "license_url": "https://creativecommons.org/licenses/by-sa/2.5",
  "artist": "Oakenking at en.wikipedia",
  "credit": "Own work",
  "sketch": "/media/herbs/jiang_can/sketch.png",
  "source": "/media/herbs/jiang_can/source.jpg",
  "attribution": "Image: Oakenking at en.wikipedia / CC BY-SA 2.5; pencil sketch derived locally for Herba Atlas."
}