{
  "key": "suan_zao_ren",
  "name_zh": "酸枣仁",
  "ok": true,
  "resolve": "wikidata:Q1420605",
  "filename": "Golop - Palace.jpg",
  "commons_title": "File:Golop - Palace.jpg",
  "source_page": "https://commons.wikimedia.org/wiki/File%3AGolop%20-%20Palace.jpg",
  "license": "CC BY-SA 2.5",
  "license_url": "https://creativecommons.org/licenses/by-sa/2.5",
  "artist": "Unknown authorUnknown author",
  "credit": "Civertan Grafikai Stúdió",
  "sketch": "/media/herbs/suan_zao_ren/sketch.png",
  "source": "/media/herbs/suan_zao_ren/source.jpg",
  "attribution": "Image: Unknown authorUnknown author / CC BY-SA 2.5; pencil sketch derived locally for Herba Atlas."
}